odoo10_addon_account_payment_credit_card-10.0.1.0.0.99.dev10-py2.7-nspkg.pth
odoo/addons/account_payment_credit_card/README.rst
odoo/addons/account_payment_credit_card/__init__.py
odoo/addons/account_payment_credit_card/__manifest__.py
odoo/addons/account_payment_credit_card/i18n/account_payment_credit_card.pot
odoo/addons/account_payment_credit_card/i18n/pt.po
odoo/addons/account_payment_credit_card/models/__init__.py
odoo/addons/account_payment_credit_card/models/account.py
odoo/addons/account_payment_credit_card/models/account_move.py
odoo/addons/account_payment_credit_card/static/description/icon.png
odoo/addons/account_payment_credit_card/views/account_view.xml
odoo10_addon_account_payment_credit_card-10.0.1.0.0.99.dev10.dist-info/METADATA
odoo10_addon_account_payment_credit_card-10.0.1.0.0.99.dev10.dist-info/RECORD
odoo10_addon_account_payment_credit_card-10.0.1.0.0.99.dev10.dist-info/WHEEL
odoo10_addon_account_payment_credit_card-10.0.1.0.0.99.dev10.dist-info/namespace_packages.txt
odoo10_addon_account_payment_credit_card-10.0.1.0.0.99.dev10.dist-info/top_level.txt
